AUTHORS.rst
CHANGELOG.rst
CONTRIBUTING.rst
LICENSE
MANIFEST.in
README.rst
setup.cfg
setup.py
versioneer.py
docs/Makefile
docs/authors.rst
docs/conf.py
docs/contributing.rst
docs/history.rst
docs/index.rst
docs/installation.rst
docs/make.bat
docs/readme.rst
docs/usage.rst
sql_query_tools/__init__.py
sql_query_tools/_version.py
sql_query_tools/utils.py
sql_query_tools.egg-info/PKG-INFO
sql_query_tools.egg-info/SOURCES.txt
sql_query_tools.egg-info/dependency_links.txt
sql_query_tools.egg-info/not-zip-safe
sql_query_tools.egg-info/top_level.txt
tests/__init__.py
tests/test_sql_query_tools.py