Metadata-Version: 2.1
Name: sql-query-tools
Version: 1.0.4
Summary: Convenient utilities for querying various flavors of SQL databases.
Home-page: https://github.com/tsouchlarakis/sql_query_tools
Author: Andoni Sooklaris
Author-email: andoni.sooklaris@gmail.com
License: MIT license
Keywords: sql_query_tools
Platform: UNKNOWN
Classifier: Development Status :: 2 - Pre-Alpha
Classifier: Intended Audience :: Developers
Classifier: License :: OSI Approved :: MIT License
Classifier: Natural Language :: English
Classifier: Programming Language :: Python :: 3
Classifier: Programming Language :: Python :: 3.6
Classifier: Programming Language :: Python :: 3.7
Classifier: Programming Language :: Python :: 3.8
Requires-Python: >=3.6
License-File: LICENSE
License-File: AUTHORS.rst
